model_controller/__init__.py
model_controller/admins.py
model_controller/apps.py
model_controller/fields.py
model_controller/forms.py
model_controller/managers.py
model_controller/mixins.py
model_controller/models.py
model_controller/queryset.py
model_controller/serializers.py
model_controller/utils.py
model_controller/views.py
django_model_controller-0.4.6.dist-info/LICENSE.md
django_model_controller-0.4.6.dist-info/METADATA
django_model_controller-0.4.6.dist-info/WHEEL
django_model_controller-0.4.6.dist-info/top_level.txt
django_model_controller-0.4.6.dist-info/RECORD
