Metadata-Version: 2.1
Name: django-model-controller
Version: 0.4.6
Summary: A model tracking field
Home-page: https://github.com/NorakGithub/django-model-controller
Author: Khemanorak Khath
Author-email: khath.khemanorak@google.com
License: BSD
Keywords: django model controller tracking
Classifier: Environment :: Web Environment
Classifier: Framework :: Django
Classifier: Framework :: Django :: 3.0
Classifier: Intended Audience :: Developers
Classifier: License :: OSI Approved :: BSD License
Classifier: Operating System :: OS Independent
Classifier: Programming Language :: Python :: 3.6
Classifier: Topic :: Internet :: WWW/HTTP
License-File: LICENSE.md
Requires-Dist: django (>=1.7)
Requires-Dist: django-braces (>=1.8.1)
Requires-Dist: django-crispy-forms (>=1.6.1)
